mviewer/Mviewer.py
mviewer/__init__.py
mviewer/_imports_.py
mviewer/metadata.json
mviewer/mviewer.min.js
mviewer/mviewer.min.js.map
mviewer/package-info.json
mviewer-1.0.1.dist-info/LICENSE
mviewer-1.0.1.dist-info/METADATA
mviewer-1.0.1.dist-info/WHEEL
mviewer-1.0.1.dist-info/top_level.txt
mviewer-1.0.1.dist-info/RECORD
