Metadata-Version: 2.2
Name: mviewer
Version: 1.0.1
Summary: Interactive astronomical image viewer.
Home-page: http://montage.ipac.caltech.edu/docs/mViewer_DASH/
Author: John Good <jcg@caltech.edu>
License: BSD-3-Clause
Classifier: Framework :: Dash
License-File: LICENSE
Dynamic: author
Dynamic: classifier
Dynamic: description
Dynamic: description-content-type
Dynamic: home-page
Dynamic: license
Dynamic: summary
